pyscrlink/__init__.py
pyscrlink/__main__.py
pyscrlink/bluepy_helper_cap.py
pyscrlink/gencert.py
pyscrlink/scratch_link.py
pyscrlink-0.2.8.dist-info/LICENSE
pyscrlink-0.2.8.dist-info/METADATA
pyscrlink-0.2.8.dist-info/WHEEL
pyscrlink-0.2.8.dist-info/entry_points.txt
pyscrlink-0.2.8.dist-info/top_level.txt
pyscrlink-0.2.8.dist-info/RECORD
