Metadata-Version: 2.1
Name: pyscrlink
Version: 0.2.8
Summary: Scratch-link for Linux with Python
Home-page: https://github.com/kawasaki/pyscrlink
Author: Shin'ichiro Kawasaki
Author-email: kawasaki@juno.dti.ne.jp
Classifier: Programming Language :: Python :: 3.6
Classifier: License :: OSI Approved :: BSD License
Classifier: Operating System :: POSIX :: Linux
Requires-Python: >=3.6
License-File: LICENSE
Requires-Dist: websockets
Requires-Dist: bluepy
Requires-Dist: pyOpenSSL
